Workbook

Sheet RAW DATA
A1: CUSTOMER ID | B1: GENDER | C1: AGE | D1: CITY | E1: SIGNUP DATE | F1: ORDER ID | G1: ORDER DATE | H1: RESTAURANT NAME | I1: DISH NAME | J1: CATEGORY | K1: QUANTITY | L1: PRICE | M1: PAYMENT METHOD | N1: ORDER FREQUENCY | O1: LAST ORDER DATE | P1: LOYALTY POINTS | Q1: CHURNED | R1: RATING | S1: RATING DATE | T1: DELIVERY STATUS | U1: REVENUE
A2: C3497 | B2: Other | C2: Senior | D2: Lahore | E2: 45461 | F2: O7497 | G2: 45404 | H2: McDonald's | I2: Sandwich | J2: Chinese | K2: 4 | L2: 222.31 | M2: Wallet | N2: 4 | O2: 45788 | P2: 450 | Q2: Inactive | R2: 4 | S2: 45816 | T2: Delivered | U2: =Table1[[#This Row],[QUANTITY]]*Table1[[#This Row],[PRICE]] -> 889.24
A3: C4774 | B3: Other | C3: Adult | D3: Islamabad | E3: 45259 | F3: O8774 | G3: 45405 | H3: Burger King | I3: Fries | J3: Italian | K3: 3 | L3: 509.02 | M3: Cash | N3: 46 | O3: 45621 | P3: 193 | Q3: Active | S3: 45751 | T3: Cancelled | U3: =Table1[[#This Row],[QUANTITY]]*Table1[[#This Row],[PRICE]] -> 1527.06
A4: C1965 | B4: Female | C4: Teenager | D4: Lahore | E4: 45641 | F4: O5965 | G4: 45405 | H4: Pizza Hut | I4: Fries | J4: Italian | K4: 2 | L4: 321.96 | M4: Wallet | N4: 25 | O4: 45847 | P4: 222 | Q4: Inactive | S4: 45815 | T4: Cancelled | U4: =Table1[[#This Row],[QUANTITY]]*Table1[[#This Row],[PRICE]] -> 643.92
A5: C4045 | B5: Other | C5: Teenager | D5: Multan | E5: 45692 | F5: O8045 | G5: 45405 | H5: Pizza Hut | I5: Fries | J5: Fast Food | K5: 4 | L5: 889.71 | M5: Cash | N5: 13 | O5: 45694 | P5: 126 | Q5: Active | R5: 4 | S5: 45637 | T5: Delayed | U5: =Table1[[#This Row],[QUANTITY]]*Table1[[#This Row],[PRICE]] -> 3558.84
A6: C6269 | B6: Female | C6: Adult | D6: Islamabad | E6: 45595 | F6: O10269 | G6: 45405 | H6: Pizza Hut | I6: Pasta | J6: Fast Food | K6: 4 | L6: 163.58 | M6: Card | N6: 6 | O6: 45858 | P6: 272 | Q6: Active | S6: 45721 | T6: Cancelled | U6: =Table1[[#This Row],[QUANTITY]]*Table1[[#This Row],[PRICE]] -> 654.32
A7: C1210 | B7: Other | C7: Adult | D7: Multan | E7: 45482 | F7: O5210 | G7: 45405 | H7: McDonald's | I7: Sandwich | J7: Dessert | K7: 3 | L7: 1259.72 | M7: Card | N7: 39 | O7: 45759 | P7: 59 | Q7: Inactive | R7: 1 | S7: 45842 | T7: Delayed | U7: =Table1[[#This Row],[QUANTITY]]*Table1[[#This Row],[PRICE]] -> 3779.16
A8: C4850 | B8: Other | C8: Teenager | D8: Islamabad | E8: 45852 | F8: O8850 | G8: 45405 | H8: Subway | I8: Sandwich | J8: Italian | K8: 1 | L8: 452.54 | M8: Cash | N8: 27 | O8: 45838 | P8: 467 | Q8: Inactive | R8: 5 | S8: 45598 | T8: Delayed | U8: =Table1[[#This Row],[QUANTITY]]*Table1[[#This Row],[PRICE]] -> 452.54
A9: C2443 | B9: Male | C9: Adult | D9: Islamabad | E9: 45169 | F9: O6443 | G9: 45405 | H9: Pizza Hut | I9: Sandwich | J9: Continental | K9: 3 | L9: 1399.51 | M9: Card | N9: 6 | O9: 45712 | P9: 4 | Q9: Inactive | S9: 45535 | T9: Cancelled | U9: =Table1[[#This Row],[QUANTITY]]*Table1[[#This Row],[PRICE]] -> 4198.53
A10: C4874 | B10: Female | C10: Teenager | D10: Lahore | E10: 45392 | F10: O8874 | G10: 45405 | H10: Pizza Hut | I10: Burger | J10: Continental | K10: 1 | L10: 501.59 | M10: Card | N10: 4 | O10: 45698 | P10: 139 | Q10: Inactive | R10: 2 | S10: 45549 | T10: Delayed | U10: =Table1[[#This Row],[QUANTITY]]*Table1[[#This Row],[PRICE]] -> 501.59
A11: C2206 | B11: Other | C11: Senior | D11: Peshawar | E11: 45372 | F11: O6206 | G11: 45405 | H11: Burger King | I11: Pizza | J11: Continental | K11: 5 | L11: 783.53 | M11: Card | N11: 11 | O11: 45718 | P11: 276 | Q11: Active | R11: 2 | S11: 45789 | T11: Delivered | U11: =Table1[[#This Row],[QUANTITY]]*Table1[[#This Row],[PRICE]] -> 3917.65
A12: C5783 | B12: Female | C12: Teenager | D12: Multan | E12: 45837 | F12: O9783 | G12: 45405 | H12: Pizza Hut | I12: Pasta | J12: Continental | K12: 4 | L12: 364.24 | M12: Card | N12: 25 | O12: 45695 | P12: 220 | Q12: Inactive | R12: 2 | S12: 45880 | T12: Delayed | U12: =Table1[[#This Row],[QUANTITY]]*Table1[[#This Row],[PRICE]] -> 1456.96
A13: C4712 | B13: Male | C13: Adult | D13: Peshawar | E13: 45236 | F13: O8712 | G13: 45405 | H13: Burger King | I13: Pasta | J13: Chinese | K13: 4 | L13: 1251.7 | M13: Card | N13: 22 | O13: 45857 | P13: 218 | Q13: Inactive | R13: 2 | S13: 45825 | T13: Delayed | U13: =Table1[[#This Row],[QUANTITY]]*Table1[[#This Row],[PRICE]] -> 5006.8
A14: C3132 | B14: Male | C14: Adult | D14: Islamabad | E14: 45702 | F14: O7132 | G14: 45406 | H14: KFC | I14: Burger | J14: Fast Food | K14: 4 | L14: 417.39 | M14: Wallet | N14: 37 | O14: 45573 | P14: 180 | Q14: Active | R14: 3 | S14: 45633 | T14: Delivered | U14: =Table1[[#This Row],[QUANTITY]]*Table1[[#This Row],[PRICE]] -> 1669.56
A15: C3540 | B15: Male | C15: Senior | D15: Islamabad | E15: 45254 | F15: O7540 | G15: 45406 | H15: KFC | I15: Pasta | J15: Fast Food | K15: 1 | L15: 153.81 | M15: Card | N15: 17 | O15: 45706 | P15: 106 | Q15: Active | R15: 3 | S15: 45653 | T15: Delayed | U15: =Table1[[#This Row],[QUANTITY]]*Table1[[#This Row],[PRICE]] -> 153.81
A16: C4265 | B16: Other | C16: Adult | D16: Multan | E16: 45368 | F16: O8265 | G16: 45406 | H16: Burger King | I16: Fries | J16: Fast Food | K16: 3 | L16: 606.24 | M16: Cash | N16: 10 | O16: 45610 | P16: 125 | Q16: Inactive | R16: 2 | S16: 45771 | T16: Delayed | U16: =Table1[[#This Row],[QUANTITY]]*Table1[[#This Row],[PRICE]] -> 1818.72
A17: C6582 | B17: Female | C17: Teenager | D17: Islamabad | E17: 45211 | F17: O10582 | G17: 45406 | H17: Burger King | I17: Burger | J17: Dessert | K17: 4 | L17: 1220.38 | M17: Cash | N17: 42 | O17: 45833 | P17: 409 | Q17: Active | S17: 45546 | T17: Cancelled | U17: =Table1[[#This Row],[QUANTITY]]*Table1[[#This Row],[PRICE]] -> 4881.52
A18: C3195 | B18: Other | C18: Adult | D18: Karachi | E18: 45838 | F18: O7195 | G18: 45406 | H18: Burger King | I18: Pizza | J18: Fast Food | K18: 5 | L18: 1300.96 | M18: Card | N18: 8 | O18: 45698 | P18: 269 | Q18: Inactive | S18: 45590 | T18: Cancelled | U18: =Table1[[#This Row],[QUANTITY]]*Table1[[#This Row],[PRICE]] -> 6504.8
A19: C3466 | B19: Male | C19: Senior | D19: Karachi | E19: 45241 | F19: O7466 | G19: 45406 | H19: McDonald's | I19: Pasta | J19: Italian | K19: 4 | L19: 476.38 | M19: Wallet | N19: 27 | O19: 45624 | P19: 222 | Q19: Inactive | S19: 45785 | T19: Cancelled | U19: =Table1[[#This Row],[QUANTITY]]*Table1[[#This Row],[PRICE]] -> 1905.52
A20: C2671 | B20: Female | C20: Senior | D20: Multan | E20: 45603 | F20: O6671 | G20: 45406 | H20: McDonald's | I20: Sandwich | J20: Chinese | K20: 3 | L20: 644.27 | M20: Cash | N20: 17 | O20: 45638 | P20: 265 | Q20: Inactive | R20: 2 | S20: 45821 | T20: Delivered | U20: =Table1[[#This Row],[QUANTITY]]*Table1[[#This Row],[PRICE]] -> 1932.81
A21: C4172 | B21: Female | C21: Teenager | D21: Karachi | E21: 45515 | F21: O8172 | G21: 45406 | H21: McDonald's | I21: Sandwich | J21: Continental | K21: 1 | L21: 125.81 | M21: Card | N21: 47 | O21: 45755 | P21: 311 | Q21: Active | S21: 45635 | T21: Cancelled | U21: =Table1[[#This Row],[QUANTITY]]*Table1[[#This Row],[PRICE]] -> 125.81
A22: C1254 | B22: Other | C22: Adult | D22: Islamabad | E22: 45286 | F22: O5254 | G22: 45406 | H22: Pizza Hut | I22: Sandwich | J22: Continental | K22: 1 | L22: 1492.01 | M22: Cash | N22: 28 | O22: 45725 | P22: 433 | Q22: Active | S22: 45559 | T22: Cancelled | U22: =Table1[[#This Row],[QUANTITY]]*Table1[[#This Row],[PRICE]] -> 1492.01
A23: C5660 | B23: Male | C23: Adult | D23: Karachi | E23: 45784 | F23: O9660 | G23: 45406 | H23: Burger King | I23: Pasta | J23: Italian | K23: 4 | L23: 1498.16 | M23: Cash | N23: 42 | O23: 45638 | P23: 446 | Q23: Active | R23: 4 | S23: 45606 | T23: Delivered | U23: =Table1[[#This Row],[QUANTITY]]*Table1[[#This Row],[PRICE]] -> 5992.64
A24: C1071 | B24: Male | C24: Senior | D24: Peshawar | E24: 45384 | F24: O5071 | G24: 45406 | H24: Pizza Hut | I24: Pizza | J24: Italian | K24: 4 | L24: 793.19 | M24: Wallet | N24: 32 | O24: 45693 | P24: 133 | Q24: Active | R24: 1 | S24: 45528 | T24: Delivered | U24: =Table1[[#This Row],[QUANTITY]]*Table1[[#This Row],[PRICE]] -> 3172.76
A25: C2643 | B25: Male | C25: Senior | D25: Islamabad | E25: 45596 | F25: O6643 | G25: 45406 | H25: Pizza Hut | I25: Sandwich | J25: Continental | K25: 5 | L25: 322.77 | M25: Card | N25: 48 | O25: 45660 | P25: 405 | Q25: Inactive | R25: 1 | S25: 45653 | T25: Delayed | U25: =Table1[[#This Row],[QUANTITY]]*Table1[[#This Row],[PRICE]] -> 1613.85
A26: C5290 | B26: Other | C26: Senior | D26: Karachi | E26: 45497 | F26: O9290 | G26: 45407 | H26: McDonald's | I26: Fries | J26: Chinese | K26: 2 | L26: 1255.34 | M26: Card | N26: 42 | O26: 45620 | P26: 102 | Q26: Inactive | S26: 45784 | T26: Cancelled | U26: =Table1[[#This Row],[QUANTITY]]*Table1[[#This Row],[PRICE]] -> 2510.68
A27: C2622 | B27: Male | C27: Teenager | D27: Karachi | E27: 45246 | F27: O6622 | G27: 45407 | H27: Burger King | I27: Fries | J27: Chinese | K27: 2 | L27: 1048.17 | M27: Wallet | N27: 9 | O27: 45752 | P27: 407 | Q27: Active | R27: 3 | S27: 45624 | T27: Delivered | U27: =Table1[[#This Row],[QUANTITY]]*Table1[[#This Row],[PRICE]] -> 2096.34
A28: C2365 | B28: Other | C28: Teenager | D28: Multan | E28: 45475 | F28: O6365 | G28: 45407 | H28: Subway | I28: Pasta | J28: Chinese | K28: 5 | L28: 1315.23 | M28: Card | N28: 21 | O28: 45742 | P28: 155 | Q28: Active | R28: 1 | S28: 45650 | T28: Delivered | U28: =Table1[[#This Row],[QUANTITY]]*Table1[[#This Row],[PRICE]] -> 6576.15
A29: C3943 | B29: Female | C29: Teenager | D29: Multan | E29: 45837 | F29: O7943 | G29: 45407 | H29: McDonald's | I29: Pizza | J29: Italian | K29: 1 | L29: 624.55 | M29: Wallet | N29: 13 | O29: 45676 | P29: 214 | Q29: Active | S29: 45591 | T29: Cancelled | U29: =Table1[[#This Row],[QUANTITY]]*Table1[[#This Row],[PRICE]] -> 624.55
A30: C6955 | B30: Other | C30: Teenager | D30: Karachi | E30: 45808 | F30: O10955 | G30: 45407 | H30: Subway | I30: Pizza | J30: Chinese | K30: 2 | L30: 751.25 | M30: Card | N30: 1 | O30: 45860 | P30: 77 | Q30: Inactive | R30: 5 | S30: 45624 | T30: Delivered | U30: =Table1[[#This Row],[QUANTITY]]*Table1[[#This Row],[PRICE]] -> 1502.5
A31: C1850 | B31: Male | C31: Teenager | D31: Karachi | E31: 45198 | F31: O5850 | G31: 45407 | H31: Pizza Hut | I31: Fries | J31: Continental | K31: 3 | L31: 726.99 | M31: Wallet | N31: 28 | O31: 45544 | P31: 192 | Q31: Inactive | R31: 3 | S31: 45605 | T31: Delivered | U31: =Table1[[#This Row],[QUANTITY]]*Table1[[#This Row],[PRICE]] -> 2180.97
A32: C5984 | B32: Male | C32: Senior | D32: Islamabad | E32: 45601 | F32: O9984 | G32: 45407 | H32: Burger King | I32: Fries | J32: Italian | K32: 1 | L32: 654.82 | M32: Cash | N32: 47 | O32: 45829 | P32: 177 | Q32: Active | R32: 1 | S32: 45568 | T32: Delayed | U32: =Table1[[#This Row],[QUANTITY]]*Table1[[#This Row],[PRICE]] -> 654.82
A33: C6458 | B33: Male | C33: Adult | D33: Peshawar | E33: 45487 | F33: O10458 | G33: 45407 | H33: Pizza Hut | I33: Pasta | J33: Dessert | K33: 3 | L33: 341.78 | M33: Cash | N33: 19 | O33: 45605 | P33: 3 | Q33: Inactive | R33: 2 | S33: 45793 | T33: Delayed | U33: =Table1[[#This Row],[QUANTITY]]*Table1[[#This Row],[PRICE]] -> 1025.34
A34: C2096 | B34: Female | C34: Teenager | D34: Peshawar | E34: 45573 | F34: O6096 | G34: 45407 | H34: Pizza Hut | I34: Sandwich | J34: Italian | K34: 2 | L34: 1226.31 | M34: Card | N34: 13 | O34: 45605 | P34: 272 | Q34: Inactive | R34: 4 | S34: 45851 | T34: Delayed | U34: =Table1[[#This Row],[QUANTITY]]*Table1[[#This Row],[PRICE]] -> 2452.62
A35: C3169 | B35: Female | C35: Adult | D35: Peshawar | E35: 45367 | F35: O7169 | G35: 45407 | H35: Pizza Hut | I35: Burger | J35: Chinese | K35: 5 | L35: 466.95 | M35: Card | N35: 15 | O35: 45818 | P35: 436 | Q35: Inactive | R35: 3 | S35: 45822 | T35: Delayed | U35: =Table1[[#This Row],[QUANTITY]]*Table1[[#This Row],[PRICE]] -> 2334.75
A36: C5924 | B36: Female | C36: Adult | D36: Karachi | E36: 45383 | F36: O9924 | G36: 45408 | H36: McDonald's | I36: Fries | J36: Fast Food | K36: 1 | L36: 1098.54 | M36: Wallet | N36: 13 | O36: 45813 | P36: 15 | Q36: Active | R36: 4 | S36: 45643 | T36: Delayed | U36: =Table1[[#This Row],[QUANTITY]]*Table1[[#This Row],[PRICE]] -> 1098.54
A37: C5556 | B37: Female | C37: Adult | D37: Lahore | E37: 45390 | F37: O9556 | G37: 45408 | H37: KFC | I37: Pizza | J37: Italian | K37: 4 | L37: 285.59 | M37: Cash | N37: 45 | O37: 45650 | P37: 263 | Q37: Inactive | R37: 4 | S37: 45537 | T37: Delayed | U37: =Table1[[#This Row],[QUANTITY]]*Table1[[#This Row],[PRICE]] -> 1142.36
A38: C3430 | B38: Other | C38: Teenager | D38: Lahore | E38: 45429 | F38: O7430 | G38: 45408 | H38: Burger King | I38: Sandwich | J38: Chinese | K38: 2 | L38: 1283.58 | M38: Wallet | N38: 49 | O38: 45678 | P38: 375 | Q38: Inactive | R38: 1 | S38: 45644 | T38: Delivered | U38: =Table1[[#This Row],[QUANTITY]]*Table1[[#This Row],[PRICE]] -> 2567.16
A39: C3013 | B39: Female | C39: Teenager | D39: Multan | E39: 45328 | F39: O7013 | G39: 45408 | H39: Subway | I39: Fries | J39: Continental | K39: 1 | L39: 240.55 | M39: Wallet | N39: 47 | O39: 45853 | P39: 412 | Q39: Inactive | S39: 45815 | T39: Cancelled | U39: =Table1[[#This Row],[QUANTITY]]*Table1[[#This Row],[PRICE]] -> 240.55
A40: C1478 | B40: Other | C40: Adult | D40: Karachi | E40: 45527 | F40: O5478 | G40: 45408 | H40: Subway | I40: Sandwich | J40: Fast Food | K40: 5 | L40: 481.17 | M40: Card | N40: 48 | O40: 45718 | P40: 391 | Q40: Inactive | S40: 45578 | T40: Cancelled | U40: =Table1[[#This Row],[QUANTITY]]*Table1[[#This Row],[PRICE]] -> 2405.85
A41: C3423 | B41: Other | C41: Adult | D41: Karachi | E41: 45705 | F41: O7423 | G41: 45408 | H41: KFC | I41: Pasta | J41: Chinese | K41: 3 | L41: 1387.34 | M41: Card | N41: 40 | O41: 45564 | P41: 51 | Q41: Active | S41: 45746 | T41: Cancelled | U41: =Table1[[#This Row],[QUANTITY]]*Table1[[#This Row],[PRICE]] -> 4162.02
A42: C4641 | B42: Other | C42: Teenager | D42: Multan | E42: 45217 | F42: O8641 | G42: 45408 | H42: Burger King | I42: Burger | J42: Continental | K42: 3 | L42: 1011.78 | M42: Wallet | N42: 25 | O42: 45568 | P42: 39 | Q42: Inactive | R42: 4 | S42: 45839 | T42: Delayed | U42: =Table1[[#This Row],[QUANTITY]]*Table1[[#This Row],[PRICE]] -> 3035.34
A43: C2409 | B43: Female | C43: Senior | D43: Karachi | E43: 45344 | F43: O6409 | G43: 45408 | H43: Pizza Hut | I43: Sandwich | J43: Dessert | K43: 2 | L43: 1363.15 | M43: Cash | N43: 32 | O43: 45663 | P43: 471 | Q43: Inactive | R43: 2 | S43: 45572 | T43: Delivered | U43: =Table1[[#This Row],[QUANTITY]]*Table1[[#This Row],[PRICE]] -> 2726.3
A44: C2863 | B44: Male | C44: Teenager | D44: Karachi | E44: 45462 | F44: O6863 | G44: 45408 | H44: Pizza Hut | I44: Pasta | J44: Italian | K44: 3 | L44: 1204.55 | M44: Card | N44: 47 | O44: 45754 | P44: 400 | Q44: Inactive | R44: 3 | S44: 45779 | T44: Delayed | U44: =Table1[[#This Row],[QUANTITY]]*Table1[[#This Row],[PRICE]] -> 3613.65
A45: C5063 | B45: Other | C45: Senior | D45: Islamabad | E45: 45433 | F45: O9063 | G45: 45409 | H45: KFC | I45: Pasta | J45: Chinese | K45: 2 | L45: 966.48 | M45: Card | N45: 5 | O45: 45778 | P45: 195 | Q45: Active | R45: 2 | S45: 45849 | T45: Delayed | U45: =Table1[[#This Row],[QUANTITY]]*Table1[[#This Row],[PRICE]] -> 1932.96
A46: C4885 | B46: Other | C46: Senior | D46: Peshawar | E46: 45389 | F46: O8885 | G46: 45409 | H46: Pizza Hut | I46: Fries | J46: Italian | K46: 2 | L46: 1333.77 | M46: Cash | N46: 26 | O46: 45731 | P46: 272 | Q46: Active | S46: 45855 | T46: Cancelled | U46: =Table1[[#This Row],[QUANTITY]]*Table1[[#This Row],[PRICE]] -> 2667.54
A47: C1904 | B47: Other | C47: Teenager | D47: Peshawar | E47: 45206 | F47: O5904 | G47: 45409 | H47: McDonald's | I47: Pizza | J47: Fast Food | K47: 3 | L47: 623.06 | M47: Cash | N47: 26 | O47: 45764 | P47: 440 | Q47: Inactive | R47: 4 | S47: 45702 | T47: Delivered | U47: =Table1[[#This Row],[QUANTITY]]*Table1[[#This Row],[PRICE]] -> 1869.18
A48: C3307 | B48: Other | C48: Adult | D48: Lahore | E48: 45788 | F48: O7307 | G48: 45409 | H48: Subway | I48: Sandwich | J48: Italian | K48: 5 | L48: 191.04 | M48: Card | N48: 5 | O48: 45652 | P48: 210 | Q48: Active | R48: 3 | S48: 45758 | T48: Delivered | U48: =Table1[[#This Row],[QUANTITY]]*Table1[[#This Row],[PRICE]] -> 955.2
A49: C1585 | B49: Female | C49: Teenager | D49: Multan | E49: 45738 | F49: O5585 | G49: 45409 | H49: Pizza Hut | I49: Burger | J49: Italian | K49: 2 | L49: 957.04 | M49: Wallet | N49: 47 | O49: 45595 | P49: 380 | Q49: Inactive | S49: 45752 | T49: Cancelled | U49: =Table1[[#This Row],[QUANTITY]]*Table1[[#This Row],[PRICE]] -> 1914.08
A50: C3661 | B50: Other | C50: Adult | D50: Islamabad | E50: 45431 | F50: O7661 | G50: 45409 | H50: KFC | I50: Pizza | J50: Continental | K50: 4 | L50: 1012.57 | M50: Wallet | N50: 26 | O50: 45528 | P50: 463 | Q50: Inactive | R50: 2 | S50: 45589 | T50: Delayed | U50: =Table1[[#This Row],[QUANTITY]]*Table1[[#This Row],[PRICE]] -> 4050.28
A51: C2438 | B51: Female | C51: Teenager | D51: Peshawar | E51: 45393 | F51: O6438 | G51: 45409 | H51: Subway | I51: Fries | J51: Italian | K51: 1 | L51: 1154.18 | M51: Cash | N51: 23 | O51: 45580 | P51: 448 | Q51: Inactive | R51: 2 | S51: 45859 | T51: Delivered | U51: =Table1[[#This Row],[QUANTITY]]*Table1[[#This Row],[PRICE]] -> 1154.18
A52: C6936 | B52: Female | C52: Adult | D52: Multan | E52: 45312 | F52: O10936 | G52: 45409 | H52: Subway | I52: Burger | J52: Chinese | K52: 4 | L52: 1227.07 | M52: Card | N52: 11 | O52: 45750 | P52: 291 | Q52: Active | R52: 5 | S52: 45672 | T52: Delivered | U52: =Table1[[#This Row],[QUANTITY]]*Table1[[#This Row],[PRICE]] -> 4908.28
A53: C5267 | B53: Female | C53: Senior | D53: Islamabad | E53: 45162 | F53: O9267 | G53: 45409 | H53: Subway | I53: Fries | J53: Dessert | K53: 5 | L53: 188.91 | M53: Card | N53: 23 | O53: 45572 | P53: 234 | Q53: Active | R53: 5 | S53: 45707 | T53: Delivered | U53: =Table1[[#This Row],[QUANTITY]]*Table1[[#This Row],[PRICE]] -> 944.55
A54: C6514 | B54: Female | C54: Teenager | D54: Islamabad | E54: 45569 | F54: O10514 | G54: 45410 | H54: KFC | I54: Pizza | J54: Chinese | K54: 2 | L54: 820.82 | M54: Wallet | N54: 47 | O54: 45539 | P54: 294 | Q54: Inactive | R54: 4 | S54: 45578 | T54: Delivered | U54: =Table1[[#This Row],[QUANTITY]]*Table1[[#This Row],[PRICE]] -> 1641.64
A55: C5394 | B55: Other | C55: Senior | D55: Peshawar | E55: 45234 | F55: O9394 | G55: 45410 | H55: KFC | I55: Burger | J55: Chinese | K55: 4 | L55: 805.09 | M55: Cash | N55: 35 | O55: 45621 | P55: 195 | Q55: Inactive | S55: 45811 | T55: Cancelled | U55: =Table1[[#This Row],[QUANTITY]]*Table1[[#This Row],[PRICE]] -> 3220.36
A56: C4973 | B56: Other | C56: Senior | D56: Multan | E56: 45549 | F56: O8973 | G56: 45410 | H56: Burger King | I56: Burger | J56: Italian | K56: 2 | L56: 611.52 | M56: Wallet | N56: 21 | O56: 45642 | P56: 73 | Q56: Active | S56: 45860 | T56: Cancelled | U56: =Table1[[#This Row],[QUANTITY]]*Table1[[#This Row],[PRICE]] -> 1223.04
A57: C2899 | B57: Male | C57: Adult | D57: Islamabad | E57: 45662 | F57: O6899 | G57: 45410 | H57: Pizza Hut | I57: Burger | J57: Italian | K57: 5 | L57: 1071.83 | M57: Card | N57: 24 | O57: 45815 | P57: 349 | Q57: Inactive | S57: 45819 | T57: Cancelled | U57: =Table1[[#This Row],[QUANTITY]]*Table1[[#This Row],[PRICE]] -> 5359.15
A58: C2302 | B58: Other | C58: Adult | D58: Peshawar | E58: 45733 | F58: O6302 | G58: 45410 | H58: KFC | I58: Fries | J58: Dessert | K58: 1 | L58: 1145.82 | M58: Card | N58: 30 | O58: 45625 | P58: 122 | Q58: Active | S58: 45675 | T58: Cancelled | U58: =Table1[[#This Row],[QUANTITY]]*Table1[[#This Row],[PRICE]] -> 1145.82
A59: C3322 | B59: Male | C59: Teenager | D59: Karachi | E59: 45389 | F59: O7322 | G59: 45410 | H59: Pizza Hut | I59: Sandwich | J59: Continental | K59: 1 | L59: 411.37 | M59: Cash | N59: 30 | O59: 45819 | P59: 243 | Q59: Active | S59: 45863 | T59: Cancelled | U59: =Table1[[#This Row],[QUANTITY]]*Table1[[#This Row],[PRICE]] -> 411.37
A60: C1479 | B60: Other | C60: Adult | D60: Multan | E60: 45267 | F60: O5479 | G60: 45410 | H60: Pizza Hut | I60: Pasta | J60: Dessert | K60: 2 | L60: 160.82 | M60: Wallet | N60: 8 | O60: 45862 | P60: 285 | Q60: Inactive | R60: 2 | S60: 45532 | T60: Delivered | U60: =Table1[[#This Row],[QUANTITY]]*Table1[[#This Row],[PRICE]] -> 321.64
A61: C4239 | B61: Female | C61: Teenager | D61: Multan | E61: 45884 | F61: O8239 | G61: 45411 | H61: KFC | I61: Sandwich | J61: Continental | K61: 2 | L61: 1185.2 | M61: Card | N61: 46 | O61: 45882 | P61: 491 | Q61: Active | S61: 45806 | T61: Cancelled | U61: =Table1[[#This Row],[QUANTITY]]*Table1[[#This Row],[PRICE]] -> 2370.4
A62: C3707 | B62: Male | C62: Teenager | D62: Peshawar | E62: 45215 | F62: O7707 | G62: 45411 | H62: KFC | I62: Burger | J62: Italian | K62: 4 | L62: 930.85 | M62: Wallet | N62: 4 | O62: 45559 | P62: 92 | Q62: Inactive | R62: 3 | S62: 45828 | T62: Delayed | U62: =Table1[[#This Row],[QUANTITY]]*Table1[[#This Row],[PRICE]] -> 3723.4
A63: C4101 | B63: Other | C63: Teenager | D63: Karachi | E63: 45643 | F63: O8101 | G63: 45411 | H63: Subway | I63: Pasta | J63: Chinese | K63: 5 | L63: 1265.29 | M63: Wallet | N63: 4 | O63: 45583 | P63: 262 | Q63: Active | R63: 3 | S63: 45779 | T63: Delivered | U63: =Table1[[#This Row],[QUANTITY]]*Table1[[#This Row],[PRICE]] -> 6326.45
A64: C3142 | B64: Female | C64: Adult | D64: Peshawar | E64: 45644 | F64: O7142 | G64: 45411 | H64: Pizza Hut | I64: Fries | J64: Dessert | K64: 3 | L64: 300.18 | M64: Cash | N64: 3 | O64: 45668 | P64: 411 | Q64: Active | S64: 45672 | T64: Cancelled | U64: =Table1[[#This Row],[QUANTITY]]*Table1[[#This Row],[PRICE]] -> 900.54
A65: C4371 | B65: Other | C65: Adult | D65: Peshawar | E65: 45591 | F65: O8371 | G65: 45411 | H65: Pizza Hut | I65: Sandwich | J65: Fast Food | K65: 1 | L65: 494.13 | M65: Card | N65: 6 | O65: 45775 | P65: 262 | Q65: Active | R65: 4 | S65: 45702 | T65: Delivered | U65: =Table1[[#This Row],[QUANTITY]]*Table1[[#This Row],[PRICE]] -> 494.13
A66: C1980 | B66: Female | C66: Senior | D66: Multan | E66: 45348 | F66: O5980 | G66: 45411 | H66: Subway | I66: Pasta | J66: Continental | K66: 3 | L66: 1029.41 | M66: Card | N66: 32 | O66: 45858 | P66: 45 | Q66: Inactive | R66: 3 | S66: 45642 | T66: Delivered | U66: =Table1[[#This Row],[QUANTITY]]*Table1[[#This Row],[PRICE]] -> 3088.23
A67: C4359 | B67: Male | C67: Adult | D67: Karachi | E67: 45667 | F67: O8359 | G67: 45411 | H67: Subway | I67: Sandwich | J67: Dessert | K67: 5 | L67: 1386.81 | M67: Wallet | N67: 19 | O67: 45614 | P67: 240 | Q67: Active | R67: 1 | S67: 45556 | T67: Delivered | U67: =Table1[[#This Row],[QUANTITY]]*Table1[[#This Row],[PRICE]] -> 6934.05
A68: C2063 | B68: Other | C68: Teenager | D68: Multan | E68: 45489 | F68: O6063 | G68: 45411 | H68: KFC | I68: Burger | J68: Fast Food | K68: 3 | L68: 987.74 | M68: Cash | N68: 50 | O68: 45791 | P68: 228 | Q68: Active | R68: 1 | S68: 45814 | T68: Delivered | U68: =Table1[[#This Row],[QUANTITY]]*Table1[[#This Row],[PRICE]] -> 2963.22
A69: C2128 | B69: Female | C69: Adult | D69: Karachi | E69: 45595 | F69: O6128 | G69: 45412 | H69: KFC | I69: Fries | J69: Fast Food | K69: 1 | L69: 1275.78 | M69: Wallet | N69: 47 | O69: 45579 | P69: 351 | Q69: Inactive | R69: 1 | S69: 45858 | T69: Delivered | U69: =Table1[[#This Row],[QUANTITY]]*Table1[[#This Row],[PRICE]] -> 1275.78
A70: C4818 | B70: Female | C70: Adult | D70: Peshawar | E70: 45874 | F70: O8818 | G70: 45412 | H70: Burger King | I70: Burger | J70: Italian | K70: 4 | L70: 683.88 | M70: Wallet | N70: 33 | O70: 45746 | P70: 475 | Q70: Active | S70: 45819 | T70: Cancelled | U70: =Table1[[#This Row],[QUANTITY]]*Table1[[#This Row],[PRICE]] -> 2735.52
A71: C1758 | B71: Male | C71: Senior | D71: Peshawar | E71: 45778 | F71: O5758 | G71: 45412 | H71: McDonald's | I71: Sandwich | J71: Chinese | K71: 2 | L71: 1012.18 | M71: Wallet | N71: 35 | O71: 45679 | P71: 141 | Q71: Active | R71: 2 | S71: 45587 | T71: Delivered | U71: =Table1[[#This Row],[QUANTITY]]*Table1[[#This Row],[PRICE]] -> 2024.36
A72: C1750 | B72: Female | C72: Senior | D72: Multan | E72: 45441 | F72: O5750 | G72: 45412 | H72: Subway | I72: Pasta | J72: Continental | K72: 4 | L72: 173.93 | M72: Card | N72: 8 | O72: 45780 | P72: 310 | Q72: Active | R72: 1 | S72: 45571 | T72: Delivered | U72: =Table1[[#This Row],[QUANTITY]]*Table1[[#This Row],[PRICE]] -> 695.72
A73: C2137 | B73: Female | C73: Senior | D73: Peshawar | E73: 45852 | F73: O6137 | G73: 45412 | H73: McDonald's | I73: Pizza | J73: Continental | K73: 3 | L73: 276.4 | M73: Card | N73: 20 | O73: 45533 | P73: 216 | Q73: Inactive | S73: 45795 | T73: Cancelled | U73: =Table1[[#This Row],[QUANTITY]]*Table1[[#This Row],[PRICE]] -> 829.2
A74: C6342 | B74: Other | C74: Adult | D74: Islamabad | E74: 45218 | F74: O10342 | G74: 45412 | H74: Pizza Hut | I74: Pizza | J74: Continental | K74: 2 | L74: 375.1 | M74: Card | N74: 12 | O74: 45562 | P74: 107 | Q74: Inactive | R74: 5 | S74: 45768 | T74: Delivered | U74: =Table1[[#This Row],[QUANTITY]]*Table1[[#This Row],[PRICE]] -> 750.2
A75: C6492 | B75: Male | C75: Senior | D75: Peshawar | E75: 45424 | F75: O10492 | G75: 45413 | H75: Burger King | I75: Fries | J75: Chinese | K75: 4 | L75: 938.68 | M75: Cash | N75: 30 | O75: 45550 | P75: 367 | Q75: Inactive | R75: 2 | S75: 45547 | T75: Delayed | U75: =Table1[[#This Row],[QUANTITY]]*Table1[[#This Row],[PRICE]] -> 3754.72
A76: C6439 | B76: Male | C76: Teenager | D76: Lahore | E76: 45793 | F76: O10439 | G76: 45413 | H76: Pizza Hut | I76: Sandwich | J76: Fast Food | K76: 5 | L76: 654.41 | M76: Cash | N76: 36 | O76: 45595 | P76: 268 | Q76: Inactive | R76: 4 | S76: 45788 | T76: Delivered | U76: =Table1[[#This Row],[QUANTITY]]*Table1[[#This Row],[PRICE]] -> 3272.05
A77: C5914 | B77: Female | C77: Teenager | D77: Peshawar | E77: 45417 | F77: O9914 | G77: 45413 | H77: Subway | I77: Pizza | J77: Dessert | K77: 4 | L77: 1164.26 | M77: Cash | N77: 47 | O77: 45785 | P77: 149 | Q77: Inactive | R77: 4 | S77: 45580 | T77: Delivered | U77: =Table1[[#This Row],[QUANTITY]]*Table1[[#This Row],[PRICE]] -> 4657.04
A78: C1168 | B78: Male | C78: Senior | D78: Peshawar | E78: 45777 | F78: O5168 | G78: 45413 | H78: Subway | I78: Pasta | J78: Continental | K78: 1 | L78: 592.84 | M78: Card | N78: 39 | O78: 45804 | P78: 290 | Q78: Active | R78: 1 | S78: 45591 | T78: Delivered | U78: =Table1[[#This Row],[QUANTITY]]*Table1[[#This Row],[PRICE]] -> 592.84
A79: C2722 | B79: Other | C79: Senior | D79: Islamabad | E79: 45240 | F79: O6722 | G79: 45414 | H79: Pizza Hut | I79: Sandwich | J79: Continental | K79: 3 | L79: 1377.06 | M79: Cash | N79: 29 | O79: 45626 | P79: 372 | Q79: Inactive | R79: 1 | S79: 45784 | T79: Delivered | U79: =Table1[[#This Row],[QUANTITY]]*Table1[[#This Row],[PRICE]] -> 4131.18
A80: C5597 | B80: Other | C80: Teenager | D80: Karachi | E80: 45576 | F80: O9597 | G80: 45414 | H80: KFC | I80: Pasta | J80: Fast Food | K80: 2 | L80: 614.21 | M80: Cash | N80: 11 | O80: 45821 | P80: 361 | Q80: Inactive | R80: 1 | S80: 45652 | T80: Delayed | U80: =Table1[[#This Row],[QUANTITY]]*Table1[[#This Row],[PRICE]] -> 1228.42
A81: C5606 | B81: Male | C81: Teenager | D81: Islamabad | E81: 45580 | F81: O9606 | G81: 45414 | H81: Pizza Hut | I81: Pasta | J81: Italian | K81: 3 | L81: 576.44 | M81: Cash | N81: 43 | O81: 45884 | P81: 460 | Q81: Inactive | R81: 3 | S81: 45711 | T81: Delivered | U81: =Table1[[#This Row],[QUANTITY]]*Table1[[#This Row],[PRICE]] -> 1729.32
A82: C6136 | B82: Female | C82: Senior | D82: Karachi | E82: 45836 | F82: O10136 | G82: 45414 | H82: Burger King | I82: Sandwich | J82: Fast Food | K82: 2 | L82: 1369.3 | M82: Card | N82: 45 | O82: 45721 | P82: 48 | Q82: Inactive | R82: 5 | S82: 45780 | T82: Delivered | U82: =Table1[[#This Row],[QUANTITY]]*Table1[[#This Row],[PRICE]] -> 2738.6
A83: C1186 | B83: Male | C83: Teenager | D83: Multan | E83: 45499 | F83: O5186 | G83: 45414 | H83: Subway | I83: Sandwich | J83: Dessert | K83: 2 | L83: 436.26 | M83: Card | N83: 14 | O83: 45580 | P83: 278 | Q83: Inactive | R83: 1 | S83: 45650 | T83: Delayed | U83: =Table1[[#This Row],[QUANTITY]]*Table1[[#This Row],[PRICE]] -> 872.52
A84: C5274 | B84: Other | C84: Teenager | D84: Peshawar | E84: 45445 | F84: O9274 | G84: 45414 | H84: Pizza Hut | I84: Burger | J84: Chinese | K84: 5 | L84: 207.86 | M84: Cash | N84: 20 | O84: 45761 | P84: 251 | Q84: Active | R84: 4 | S84: 45878 | T84: Delivered | U84: =Table1[[#This Row],[QUANTITY]]*Table1[[#This Row],[PRICE]] -> 1039.3
A85: C1060 | B85: Female | C85: Adult | D85: Multan | E85: 45418 | F85: O5060 | G85: 45414 | H85: Subway | I85: Pizza | J85: Chinese | K85: 4 | L85: 340.15 | M85: Cash | N85: 44 | O85: 45818 | P85: 450 | Q85: Active | S85: 45838 | T85: Cancelled | U85: =Table1[[#This Row],[QUANTITY]]*Table1[[#This Row],[PRICE]] -> 1360.6
A86: C6584 | B86: Female | C86: Senior | D86: Islamabad | E86: 45869 | F86: O10584 | G86: 45414 | H86: Subway | I86: Fries | J86: Italian | K86: 5 | L86: 117.17 | M86: Wallet | N86: 32 | O86: 45755 | P86: 488 | Q86: Inactive | R86: 3 | S86: 45599 | T86: Delayed | U86: =Table1[[#This Row],[QUANTITY]]*Table1[[#This Row],[PRICE]] -> 585.85
A87: C2586 | B87: Other | C87: Teenager | D87: Peshawar | E87: 45865 | F87: O6586 | G87: 45414 | H87: McDonald's | I87: Burger | J87: Continental | K87: 4 | L87: 849.63 | M87: Wallet | N87: 1 | O87: 45716 | P87: 482 | Q87: Active | S87: 45621 | T87: Cancelled | U87: =Table1[[#This Row],[QUANTITY]]*Table1[[#This Row],[PRICE]] -> 3398.52
A88: C4971 | B88: Female | C88: Adult | D88: Lahore | E88: 45494 | F88: O8971 | G88: 45415 | H88: McDonald's | I88: Pizza | J88: Fast Food | K88: 4 | L88: 1349.93 | M88: Card | N88: 14 | O88: 45763 | P88: 2 | Q88: Active | S88: 45771 | T88: Cancelled | U88: =Table1[[#This Row],[QUANTITY]]*Table1[[#This Row],[PRICE]] -> 5399.72
A89: C4437 | B89: Male | C89: Teenager | D89: Karachi | E89: 45234 | F89: O8437 | G89: 45415 | H89: Burger King | I89: Sandwich | J89: Fast Food | K89: 4 | L89: 1130.54 | M89: Card | N89: 14 | O89: 45775 | P89: 315 | Q89: Active | R89: 2 | S89: 45580 | T89: Delivered | U89: =Table1[[#This Row],[QUANTITY]]*Table1[[#This Row],[PRICE]] -> 4522.16
A90: C6869 | B90: Male | C90: Teenager | D90: Multan | E90: 45681 | F90: O10869 | G90: 45415 | H90: McDonald's | I90: Burger | J90: Italian | K90: 5 | L90: 726.46 | M90: Cash | N90: 11 | O90: 45624 | P90: 386 | Q90: Inactive | R90: 4 | S90: 45647 | T90: Delivered | U90: =Table1[[#This Row],[QUANTITY]]*Table1[[#This Row],[PRICE]] -> 3632.3
A91: C1869 | B91: Female | C91: Senior | D91: Peshawar | E91: 45519 | F91: O5869 | G91: 45415 | H91: Burger King | I91: Pizza | J91: Fast Food | K91: 2 | L91: 1172.17 | M91: Cash | N91: 6 | O91: 45857 | P91: 315 | Q91: Active | S91: 45751 | T91: Cancelled | U91: =Table1[[#This Row],[QUANTITY]]*Table1[[#This Row],[PRICE]] -> 2344.34
A92: C5521 | B92: Female | C92: Adult | D92: Karachi | E92: 45479 | F92: O9521 | G92: 45415 | H92: Subway | I92: Fries | J92: Chinese | K92: 2 | L92: 702.87 | M92: Cash | N92: 20 | O92: 45836 | P92: 258 | Q92: Active | S92: 45533 | T92: Cancelled | U92: =Table1[[#This Row],[QUANTITY]]*Table1[[#This Row],[PRICE]] -> 1405.74
A93: C2229 | B93: Other | C93: Senior | D93: Multan | E93: 45431 | F93: O6229 | G93: 45415 | H93: Pizza Hut | I93: Sandwich | J93: Fast Food | K93: 5 | L93: 739.23 | M93: Wallet | N93: 33 | O93: 45782 | P93: 333 | Q93: Active | S93: 45566 | T93: Cancelled | U93: =Table1[[#This Row],[QUANTITY]]*Table1[[#This Row],[PRICE]] -> 3696.15
A94: C6830 | B94: Other | C94: Senior | D94: Lahore | E94: 45348 | F94: O10830 | G94: 45416 | H94: Pizza Hut | I94: Fries | J94: Fast Food | K94: 5 | L94: 419.55 | M94: Card | N94: 50 | O94: 45564 | P94: 241 | Q94: Active | R94: 5 | S94: 45650 | T94: Delivered | U94: =Table1[[#This Row],[QUANTITY]]*Table1[[#This Row],[PRICE]] -> 2097.75
A95: C4917 | B95: Female | C95: Adult | D95: Karachi | E95: 45744 | F95: O8917 | G95: 45416 | H95: KFC | I95: Pasta | J95: Italian | K95: 3 | L95: 876.4 | M95: Wallet | N95: 7 | O95: 45774 | P95: 137 | Q95: Active | S95: 45530 | T95: Cancelled | U95: =Table1[[#This Row],[QUANTITY]]*Table1[[#This Row],[PRICE]] -> 2629.2
A96: C1334 | B96: Other | C96: Adult | D96: Karachi | E96: 45587 | F96: O5334 | G96: 45416 | H96: KFC | I96: Fries | J96: Chinese | K96: 3 | L96: 236.93 | M96: Card | N96: 49 | O96: 45699 | P96: 446 | Q96: Active | R96: 3 | S96: 45682 | T96: Delivered | U96: =Table1[[#This Row],[QUANTITY]]*Table1[[#This Row],[PRICE]] -> 710.79
A97: C1555 | B97: Other | C97: Senior | D97: Karachi | E97: 45189 | F97: O5555 | G97: 45416 | H97: KFC | I97: Pasta | J97: Italian | K97: 1 | L97: 171.97 | M97: Wallet | N97: 19 | O97: 45544 | P97: 412 | Q97: Inactive | R97: 4 | S97: 45692 | T97: Delivered | U97: =Table1[[#This Row],[QUANTITY]]*Table1[[#This Row],[PRICE]] -> 171.97
A98: C2345 | B98: Other | C98: Senior | D98: Lahore | E98: 45523 | F98: O6345 | G98: 45416 | H98: Pizza Hut | I98: Fries | J98: Continental | K98: 5 | L98: 799.38 | M98: Wallet | N98: 42 | O98: 45618 | P98: 300 | Q98: Active | R98: 2 | S98: 45587 | T98: Delivered | U98: =Table1[[#This Row],[QUANTITY]]*Table1[[#This Row],[PRICE]] -> 3996.9
A99: C5664 | B99: Female | C99: Adult | D99: Multan | E99: 45847 | F99: O9664 | G99: 45416 | H99: KFC | I99: Pasta | J99: Continental | K99: 1 | L99: 492.37 | M99: Cash | N99: 4 | O99: 45707 | P99: 348 | Q99: Active | R99: 2 | S99: 45804 | T99: Delivered | U99: =Table1[[#This Row],[QUANTITY]]*Table1[[#This Row],[PRICE]] -> 492.37
A100: C2819 | B100: Male | C100: Adult | D100: Multan | E100: 45706 | F100: O6819 | G100: 45417 | H100: Pizza Hut | I100: Pasta | J100: Continental | K100: 3 | L100: 806.34 | M100: Card | N100: 18 | O100: 45700 | P100: 278 | Q100: Inactive | S100: 45652 | T100: Cancelled | U100: =Table1[[#This Row],[QUANTITY]]*Table1[[#This Row],[PRICE]] -> 2419.02
...

Sheet PROJECT TASK
A1: TASK #1 | D1: TASK #6 | J1: TASK #10
A2: Row Labels | B2: Sum of REVENUE | D2: Row Labels | E2: Sum of REVENUE | J2: 1. Pizza Hut leads with 265,411.62 in revenue, slightly higher than Burger King and KFC
A3: Pizza Hut | B3: 265411.62 | D3: Burger King | E3: 261988.13 | J3: 2. Multan recorded the highest number of orders among all cities
A4: Grand Total | B4: 265411.62 | D4: KFC | E4: 253854.62 | J4: 3. The majority of customers prefer paying card rather than cash or wallet
D5: McDonald's | E5: 185013.31 | J5: 4. Continental dishes sold the highest quantity among all categories
A6: TASK #2 | D6: Pizza Hut | E6: 265411.62 | J6: 5. The average customer rating is 3.08 out of 5
A7: Row Labels | B7: Count of ORDER ID | D7: Subway | E7: 233308.3
A8: Islamabad | B8: 97 | D8: Grand Total | E8: 1199576
A9: Karachi | B9: 104 | J9: Total Revenue | K9: =SUM('RAW DATA'!$U$2:$U$501) -> 1199576
A10: Lahore | B10: 85 | D10: TASK #7 | J10: Total Orders | K10: 500
A11: Multan | B11: 110 | J11: Average Rating | K11: =AVERAGE(Table1[RATING]) -> 3.0737463
A12: Peshawar | B12: 104 | J12: Quantity Sold | K12: =SUM('RAW DATA'!K2:K501) -> 1480
A13: Grand Total | B13: 500
A15: TASK #3
A16: Row Labels | B16: Count of ORDER ID
A17: Card | B17: 183
A18: Cash | B18: 162
A19: Wallet | B19: 155
A20: Grand Total | B20: 500
A22: TASK #4
A23: Average Rating | B23: =AVERAGE(Table1[RATING]) -> 3.0737463
A27: TASK #5
A28: Row Labels | B28: Sum of QUANTITY
A29: Chinese | B29: 289 | D29: TASK #8
A30: Continental | B30: 334
A31: Dessert | B31: 282
A32: Fast Food | B32: 256
A33: Italian | B33: 319
A34: Grand Total | B34: 1480

Sheet DASHBOARD
C3: DASHBOARD | H3: TOTAL ORDERS | K3: TOTAL REVENUE | M3: AVERAGE RATING | P3: QUANTITY SOLD | R3: TOTAL ORDER FREQUENCY | U3: DATE TODAY:
H4: =H34 -> 500 | K4: =Q34 -> 1199576 | M4: =M34 -> 3.081804 | P4: =K34 -> 1480 | R4: =J34 -> 13044 | U4: =TODAY() -> 46098
D5: HIGHEST REVENUE
C7: Pizza Hut
D11: MOST ORDERS | V11: PAYMENT METHOD
C13: Multan
U14: Card
V17: FOOD CATEGORY
V21: Continental
N25: ORDERS PER MONTH
D26: RESTAURANT NAME | H26: ORDERS | I26: CUSTOMERS | J26: ORDERS FREQUENCY | K26: QUANTITY SOLD | L26: AVERAGE DISH PRICE | M26: RESTAURANT RATING | N26: MAY | O26: JUNE | P26: JULY | Q26: REVENUE | T26: REVENUE SHARE
D27: BURGER KING | H27: =COUNTIF(Table1[RESTAURANT NAME], D27) -> 97 | I27: {=COUNTA(_xlfn.UNIQUE(_xlfn._xlws.FILTER(Table1[CUSTOMER ID], Table1[RESTAURANT NAME] = D27)))} -> 97 | J27: =SUMIF(Table1[RESTAURANT NAME], "Burger King", Table1[ORDER FREQUENCY]) -> 2624 | K27: =SUMIF('RAW DATA'!$H$2:$H$501, D27, 'RAW DATA'!$K$2:$K$501) -> 293 | L27: 894.16 | M27: =AVERAGEIF('RAW DATA'!$H$2:$H$501, "Burger King", 'RAW DATA'!$R$2:$R$501) -> 3.1935484 | N27: {=SUMPRODUCT(('RAW DATA'!$H$2:$H$501="Burger King")*(MONTH('RAW DATA'!$G$2:$G$501)=4))} -> 13 | O27: {=SUMPRODUCT(('RAW DATA'!$H$2:$H$501="Burger King")*(MONTH('RAW DATA'!$G$2:$G$501)=5))} -> 43 | P27: {=SUMPRODUCT(('RAW DATA'!$H$2:$H$501="Burger King")*(MONTH('RAW DATA'!$G$2:$G$501)=6))} -> 41 | Q27: =SUMIF('RAW DATA'!$H$2:$H$501, D27, 'RAW DATA'!$U$2:$U$501) -> 261988.13 | T27: =Q27/$Q$34 -> 0.21840061
D28: KFC | H28: =COUNTIF(Table1[RESTAURANT NAME], D28) -> 99 | I28: {=COUNTA(_xlfn.UNIQUE(_xlfn._xlws.FILTER(Table1[CUSTOMER ID], Table1[RESTAURANT NAME] = D28)))} -> 99 | J28: =SUMIF(Table1[RESTAURANT NAME], "KFC", Table1[ORDER FREQUENCY]) -> 2534 | K28: =SUMIF('RAW DATA'!$H$2:$H$501, D28, 'RAW DATA'!$K$2:$K$501) -> 286 | L28: 887.6 | M28: =AVERAGEIF('RAW DATA'!$H$2:$H$501, "KFC", 'RAW DATA'!$R$2:$R$501) -> 3.0135135 | N28: {=SUMPRODUCT(('RAW DATA'!$H$2:$H$501="KFC")*(MONTH('RAW DATA'!$G$2:$G$501)=4))} -> 13 | O28: {=SUMPRODUCT(('RAW DATA'!$H$2:$H$501="KFC")*(MONTH('RAW DATA'!$G$2:$G$501)=5))} -> 49 | P28: {=SUMPRODUCT(('RAW DATA'!$H$2:$H$501="KFC")*(MONTH('RAW DATA'!$G$2:$G$501)=6))} -> 37 | Q28: =SUMIF('RAW DATA'!$H$2:$H$501, D28, 'RAW DATA'!$U$2:$U$501) -> 253854.62 | T28: =Q28/$Q$34 -> 0.21162029
D29: MCDONALD'S | H29: =COUNTIF(Table1[RESTAURANT NAME], D29) -> 82 | I29: {=COUNTA(_xlfn.UNIQUE(_xlfn._xlws.FILTER(Table1[CUSTOMER ID], Table1[RESTAURANT NAME] = D29)))} -> 82 | J29: =SUMIF(Table1[RESTAURANT NAME], D29, Table1[ORDER FREQUENCY]) -> 1974 | K29: =SUMIF('RAW DATA'!$H$2:$H$501, D29, 'RAW DATA'!$K$2:$K$501) -> 236 | L29: 783.95 | M29: =AVERAGEIF('RAW DATA'!$H$2:$H$501, "McDonald's", 'RAW DATA'!$R$2:$R$501) -> 3.1481481 | N29: {=SUMPRODUCT(('RAW DATA'!$H$2:$H$501="McDonald's")*(MONTH('RAW DATA'!$G$2:$G$501)=4))} -> 11 | O29: {=SUMPRODUCT(('RAW DATA'!$H$2:$H$501="McDonald's")*(MONTH('RAW DATA'!$G$2:$G$501)=5))} -> 40 | P29: {=SUMPRODUCT(('RAW DATA'!$H$2:$H$501="McDonald's")*(MONTH('RAW DATA'!$G$2:$G$501)=6))} -> 31 | Q29: =SUMIF('RAW DATA'!$H$2:$H$501, D29, 'RAW DATA'!$U$2:$U$501) -> 185013.31 | T29: =Q29/$Q$34 -> 0.15423226
D30: PIZZA HUT | H30: =COUNTIF(Table1[RESTAURANT NAME], D30) -> 116 | I30: {=COUNTA(_xlfn.UNIQUE(_xlfn._xlws.FILTER(Table1[CUSTOMER ID], Table1[RESTAURANT NAME] = D30)))} -> 116 | J30: =SUMIF(Table1[RESTAURANT NAME], D30, Table1[ORDER FREQUENCY]) -> 3044 | K30: =SUMIF('RAW DATA'!$H$2:$H$501, D30, 'RAW DATA'!$K$2:$K$501) -> 356 | L30: 745.54 | M30: =AVERAGEIF('RAW DATA'!$H$2:$H$501, D30, 'RAW DATA'!$R$2:$R$501) -> 3.025641 | N30: {=SUMPRODUCT(('RAW DATA'!$H$2:$H$501="Pizza Hut")*(MONTH('RAW DATA'!$G$2:$G$501)=4))} -> 23 | O30: {=SUMPRODUCT(('RAW DATA'!$H$2:$H$501="Pizza Hut")*(MONTH('RAW DATA'!$G$2:$G$501)=5))} -> 56 | P30: {=SUMPRODUCT(('RAW DATA'!$H$2:$H$501="Pizza Hut")*(MONTH('RAW DATA'!$G$2:$G$501)=6))} -> 37 | Q30: =SUMIF('RAW DATA'!$H$2:$H$501, D30, 'RAW DATA'!$U$2:$U$501) -> 265411.62 | T30: =Q30/$Q$34 -> 0.22125453
D31: SUBWAY | H31: =COUNTIF(Table1[RESTAURANT NAME], D31) -> 106 | I31: {=COUNTA(_xlfn.UNIQUE(_xlfn._xlws.FILTER(Table1[CUSTOMER ID], Table1[RESTAURANT NAME] = D31)))} -> 106 | J31: =SUMIF(Table1[RESTAURANT NAME], D31, Table1[ORDER FREQUENCY]) -> 2868 | K31: =SUMIF('RAW DATA'!$H$2:$H$501, D31, 'RAW DATA'!$K$2:$K$501) -> 309 | L31: 755.04 | M31: =AVERAGEIF('RAW DATA'!$H$2:$H$501, D31, 'RAW DATA'!$R$2:$R$501) -> 3.028169 | N31: {=SUMPRODUCT(('RAW DATA'!$H$2:$H$501="Subway")*(MONTH('RAW DATA'!$G$2:$G$501)=4))} -> 13 | O31: {=SUMPRODUCT(('RAW DATA'!$H$2:$H$501="Subway")*(MONTH('RAW DATA'!$G$2:$G$501)=5))} -> 44 | P31: {=SUMPRODUCT(('RAW DATA'!$H$2:$H$501="Subway")*(MONTH('RAW DATA'!$G$2:$G$501)=6))} -> 49 | Q31: =SUMIF('RAW DATA'!$H$2:$H$501, D31, 'RAW DATA'!$U$2:$U$501) -> 233308.3 | T31: =Q31/$Q$34 -> 0.19449231
D33: OVERALL | H33: TOTAL ORDERS | I33: TOTAL CUSTOMER | J33: TOTAL ORDERS FREQUENCY | K33: TOTAL QUANTITY SOLD | L33: AVERAGE DISH PRICE | M33: AVERAGE RATING | N33: MAY ORDERS | O33: JUNE ORDERS | P33: JULY ORDERS | Q33: TOTAL REVENUE
H34: =SUM($H$27:$H$31) -> 500 | I34: =SUM($I$27:$I$31) -> 500 | J34: =SUM($J$27:$J$31) -> 13044 | K34: =SUM(K27:K31) -> 1480 | L34: =AVERAGE(L27:L31) -> 813.258 | M34: =AVERAGE(M27:M31) -> 3.081804 | N34: =SUM(N27:N31) -> 73 | O34: =SUM(O27:O31) -> 232 | P34: =SUM(P27:P31) -> 195 | Q34: =SUM($Q$27:$S$31) -> 1199576
